odoo/addons/pos_name_to_sale_order/__init__.py
odoo/addons/pos_name_to_sale_order/__manifest__.py
odoo/addons/pos_name_to_sale_order/i18n/ca_ES.po
odoo/addons/pos_name_to_sale_order/i18n/es.po
odoo/addons/pos_name_to_sale_order/models/__init__.py
odoo/addons/pos_name_to_sale_order/models/sale_order.py
odoo/addons/pos_name_to_sale_order/report/__init__.py
odoo/addons/pos_name_to_sale_order/report/sale_report.py
odoo/addons/pos_name_to_sale_order/views/sale_order.xml
odoo/addons/pos_name_to_sale_order/views/sale_report.xml
odoo12_addon_pos_name_to_sale_order-12.0.0.0.3.dist-info/METADATA
odoo12_addon_pos_name_to_sale_order-12.0.0.0.3.dist-info/WHEEL
odoo12_addon_pos_name_to_sale_order-12.0.0.0.3.dist-info/top_level.txt
odoo12_addon_pos_name_to_sale_order-12.0.0.0.3.dist-info/RECORD
